pynurex/__init__.py
pynurex/_pynurex.cp310-win_amd64.pyd
pynurex-1.9.3.dist-info/METADATA
pynurex-1.9.3.dist-info/WHEEL
pynurex-1.9.3.dist-info/licenses/LICENSE
pynurex-1.9.3.dist-info/RECORD
